executor/errors.py
executor/executor.py
executor/info.py
executor/states.py
executor/task.py
parallel_executor-1.1.dist-info/METADATA
parallel_executor-1.1.dist-info/WHEEL
parallel_executor-1.1.dist-info/top_level.txt
parallel_executor-1.1.dist-info/RECORD
